yolotext/Yolov8TextDetection.py
yolotext/__init__.py
yolotext-0.1.dist-info/METADATA
yolotext-0.1.dist-info/WHEEL
yolotext-0.1.dist-info/top_level.txt
yolotext-0.1.dist-info/RECORD
