Metadata-Version: 2.1
Name: yolotext
Version: 0.1
Requires-Dist: beautifulsoup4 ==4.12.3
Requires-Dist: certifi ==2024.2.2
Requires-Dist: charset-normalizer ==3.3.2
Requires-Dist: contourpy ==1.2.0
Requires-Dist: cycler ==0.12.1
Requires-Dist: dill ==0.3.8
Requires-Dist: filelock ==3.13.1
Requires-Dist: fonttools ==4.49.0
Requires-Dist: fsspec ==2024.2.0
Requires-Dist: gdown ==5.1.0
Requires-Dist: idna ==3.6
Requires-Dist: Jinja2 ==3.1.3
Requires-Dist: kiwisolver ==1.4.5
Requires-Dist: MarkupSafe ==2.1.5
Requires-Dist: matplotlib ==3.8.3
Requires-Dist: mpmath ==1.3.0
Requires-Dist: networkx ==3.2.1
Requires-Dist: numpy ==1.26.4
Requires-Dist: nvidia-cublas-cu12 ==12.1.3.1
Requires-Dist: nvidia-cuda-cupti-cu12 ==12.1.105
Requires-Dist: nvidia-cuda-nvrtc-cu12 ==12.1.105
Requires-Dist: nvidia-cuda-runtime-cu12 ==12.1.105
Requires-Dist: nvidia-cudnn-cu12 ==8.9.2.26
Requires-Dist: nvidia-cufft-cu12 ==11.0.2.54
Requires-Dist: nvidia-curand-cu12 ==10.3.2.106
Requires-Dist: nvidia-cusolver-cu12 ==11.4.5.107
Requires-Dist: nvidia-cusparse-cu12 ==12.1.0.106
Requires-Dist: nvidia-nccl-cu12 ==2.19.3
Requires-Dist: nvidia-nvjitlink-cu12 ==12.3.101
Requires-Dist: nvidia-nvtx-cu12 ==12.1.105
Requires-Dist: opencv-python ==4.9.0.80
Requires-Dist: packaging ==23.2
Requires-Dist: pandas ==2.2.0
Requires-Dist: pillow ==10.2.0
Requires-Dist: psutil ==5.9.8
Requires-Dist: py-cpuinfo ==9.0.0
Requires-Dist: pyparsing ==3.1.1
Requires-Dist: PySocks ==1.7.1
Requires-Dist: python-dateutil ==2.8.2
Requires-Dist: pytz ==2024.1
Requires-Dist: PyYAML ==6.0.1
Requires-Dist: requests ==2.31.0
Requires-Dist: scipy ==1.12.0
Requires-Dist: seaborn ==0.13.2
Requires-Dist: six ==1.16.0
Requires-Dist: soupsieve ==2.5
Requires-Dist: sympy ==1.12
Requires-Dist: thop ==0.1.1.post2209072238
Requires-Dist: torch ==2.2.0
Requires-Dist: torchvision ==0.17.0
Requires-Dist: tqdm ==4.66.2
Requires-Dist: triton ==2.2.0
Requires-Dist: typing-extensions ==4.9.0
Requires-Dist: tzdata ==2024.1
Requires-Dist: ultralytics ==8.1.16
Requires-Dist: urllib3 ==2.2.1
